LICENSE
MANIFEST.in
README.md
autoroutes.c
autoroutes.pyx
pyproject.toml
autoroutes.egg-info/PKG-INFO
autoroutes.egg-info/SOURCES.txt
autoroutes.egg-info/dependency_links.txt
autoroutes.egg-info/requires.txt
autoroutes.egg-info/top_level.txt
tests/test_edge.py
tests/test_routes.py