Metadata-Version: 2.1
Name: autoroutes
Version: 0.3.8
Author-email: Yohan Boniface <yohanboniface@free.fr>
License: MIT License
Project-URL: Homepage, https://github.com/pyrates/autoroutes
Classifier: License :: OSI Approved :: MIT License
Classifier: Intended Audience :: Developers
Classifier: Programming Language :: Python :: 3
Classifier: Operating System :: POSIX
Classifier: Operating System :: MacOS :: MacOS X
Classifier: Environment :: Web Environment
Classifier: Development Status :: 4 - Beta
License-File: LICENSE
Provides-Extra: dev
Requires-Dist: build; extra == "dev"
Requires-Dist: cython; extra == "dev"
Requires-Dist: pytest; extra == "dev"
Requires-Dist: twine; extra == "dev"
